puffotter/__init__.py
puffotter/crypto.py
puffotter/env.py
puffotter/graphql.py
puffotter/imap.py
puffotter/init.py
puffotter/json.py
puffotter/logging.py
puffotter/os.py
puffotter/print.py
puffotter/prompt.py
puffotter/recaptcha.py
puffotter/requests.py
puffotter/smtp.py
puffotter/subprocess.py
puffotter/testutils.py
puffotter/units.py
puffotter/test/TestCrypto.py
puffotter/test/TestOs.py
puffotter/test/TestUnits.py
puffotter/test/__init__.py
puffotter-0.17.2.dist-info/LICENSE
puffotter-0.17.2.dist-info/METADATA
puffotter-0.17.2.dist-info/WHEEL
puffotter-0.17.2.dist-info/top_level.txt
puffotter-0.17.2.dist-info/RECORD
