Metadata-Version: 2.1
Name: puffotter
Version: 0.17.2
Summary: Convenience library for python
Home-page: https://gitlab.namibsun.net/namibsun/python/puffotter
Author: Hermann Krumrey
Author-email: hermann@krumreyh.com
License: GNU GPL3
Platform: UNKNOWN
Classifier: License :: OSI Approved :: GNU General Public License v3 (GPLv3)
Requires-Dist: sentry-sdk
Requires-Dist: requests
Requires-Dist: colorama
Provides-Extra: crypto
Requires-Dist: bcrypt ; extra == 'crypto'
